skpb_toolbox/__init__.py
skpb_toolbox/numbers.py
skpb_toolbox/parsing.py
skpb_toolbox/printing.py
skpb_toolbox/py.typed
skpb_toolbox/solvers.py
skpb_toolbox/symbolic.py
skpb_toolbox-0.1.0.dist-info/METADATA
skpb_toolbox-0.1.0.dist-info/WHEEL
skpb_toolbox-0.1.0.dist-info/RECORD
