Metadata-Version: 2.4
Name: skpb-toolbox
Version: 0.1.0
Summary: Add your description here
Author-email: PBonvang <peter.bonvang@gmail.com>
Requires-Python: >=3.13
Requires-Dist: ipykernel>=6.30.1
Requires-Dist: numpy>=2.3.3
Requires-Dist: sympy>=1.14.0
